tests/__init__.py
tests/test_fbprophet_api.py
tests/test_holt_optimizer.py
tests/test_time_series.py
tests/test_data/air_passenger.csv
vf_forecaster/__init__.py
vf_forecaster/data/__init__.py
vf_forecaster/data/time_series.py
vf_forecaster/models/__init__.py
vf_forecaster/models/base_model.py
vf_forecaster/models/holt_winters.py
vf_forecaster/models/prophet.py
vf_forecaster/optimizer/__init__.py
vf_forecaster-0.6.2.dist-info/AUTHORS
vf_forecaster-0.6.2.dist-info/LICENSE
vf_forecaster-0.6.2.dist-info/METADATA
vf_forecaster-0.6.2.dist-info/WHEEL
vf_forecaster-0.6.2.dist-info/pbr.json
vf_forecaster-0.6.2.dist-info/top_level.txt
vf_forecaster-0.6.2.dist-info/RECORD
